pypdftotext/__init__.py
pypdftotext/_config.py
pypdftotext/azure_docintel_integrator.py
pypdftotext/batch.py
pypdftotext/extracted_page.py
pypdftotext/header_footer_detection.py
pypdftotext/layout.py
pypdftotext/page_fingerprint.py
pypdftotext/pdf_extract.py
pypdftotext-0.3.1.dist-info/LICENSE
pypdftotext-0.3.1.dist-info/WHEEL
pypdftotext-0.3.1.dist-info/METADATA
pypdftotext-0.3.1.dist-info/RECORD
