Metadata-Version: 2.1
Name: pypdftotext
Version: 0.3.1
Summary: Extract text from pdf pages from codebehind or Azure OCR as required
Author-email: Sam Hartzog <sam.hartzog@hank.ai>
Requires-Python: >=3.10
Classifier: Programming Language :: Python :: 3 :: Only
Classifier: Programming Language :: Python :: 3.10
Classifier: Programming Language :: Python :: 3.11
Classifier: Programming Language :: Python :: 3.12
Classifier: License :: OSI Approved :: MIT License
Classifier: Operating System :: OS Independent
Requires-Dist: pypdf==6.0
Requires-Dist: tqdm
Requires-Dist: azure-ai-documentintelligence>=1.0.0
Requires-Dist: boto3 ; extra == "dev"
Requires-Dist: pillow>=8.0.0 ; extra == "dev"
Requires-Dist: boto3-stubs[s3] ; extra == "dev"
Requires-Dist: pytest>=7.0.0 ; extra == "dev"
Requires-Dist: pytest-cov>=4.0.0 ; extra == "dev"
Requires-Dist: boto3 ; extra == "full"
Requires-Dist: pillow>=8.0.0 ; extra == "full"
Requires-Dist: pillow>=8.0.0 ; extra == "image"
Requires-Dist: boto3 ; extra == "s3"
Project-URL: Home, https://github.com/hank-ai/pypdftotext
Project-URL: Issues, https://github.com/hank-ai/pypdftotext/issues
Provides-Extra: dev
Provides-Extra: full
Provides-Extra: image
Provides-Extra: s3
